parallenv/__init__.py
parallenv/parallenv.py
parallenv/py.typed
parallenv-0.1.0.dist-info/METADATA
parallenv-0.1.0.dist-info/WHEEL
parallenv-0.1.0.dist-info/licenses/LICENSE
parallenv-0.1.0.dist-info/RECORD
