Metadata-Version: 2.4
Name: parallenv
Version: 0.1.0
Summary: Gymnasium inspired tools for (really) parallel Reinforcement Learning
Project-URL: Homepage, https://github.com/adrianpbe/ParallEnv
Author: Adrián Pascual
License: MIT License
License-File: LICENSE
Classifier: Development Status :: 3 - Alpha
Classifier: Intended Audience :: Developers
Classifier: Intended Audience :: Science/Research
Classifier: License :: OSI Approved :: MIT License
Classifier: Operating System :: OS Independent
Classifier: Programming Language :: Python
Classifier: Programming Language :: Python :: 3
Classifier: Programming Language :: Python :: 3.10
Classifier: Programming Language :: Python :: 3.11
Classifier: Programming Language :: Python :: 3.12
Classifier: Topic :: Scientific/Engineering :: Artificial Intelligence
Requires-Python: >=3.10
Requires-Dist: gymnasium>=1.1.0
